odoo/addons/server_action_domain/README.rst
odoo/addons/server_action_domain/__init__.py
odoo/addons/server_action_domain/__manifest__.py
odoo/addons/server_action_domain/i18n/hr.po
odoo/addons/server_action_domain/i18n/it.po
odoo/addons/server_action_domain/i18n/server_action_domain.pot
odoo/addons/server_action_domain/models/__init__.py
odoo/addons/server_action_domain/models/ir_actions_server.py
odoo/addons/server_action_domain/readme/CONTRIBUTORS.rst
odoo/addons/server_action_domain/readme/DESCRIPTION.rst
odoo/addons/server_action_domain/static/description/icon.png
odoo/addons/server_action_domain/static/description/index.html
odoo/addons/server_action_domain/tests/__init__.py
odoo/addons/server_action_domain/tests/test_server_action_domain.py
odoo/addons/server_action_domain/views/ir_actions_server.xml
odoo14_addon_server_action_domain-14.0.1.0.1.dev10.dist-info/METADATA
odoo14_addon_server_action_domain-14.0.1.0.1.dev10.dist-info/WHEEL
odoo14_addon_server_action_domain-14.0.1.0.1.dev10.dist-info/top_level.txt
odoo14_addon_server_action_domain-14.0.1.0.1.dev10.dist-info/RECORD
